.gitignore
offapi-0.1.2.dist-info/METADATA
offapi-0.1.2.dist-info/WHEEL
offapi-0.1.2.dist-info/entry_points.txt
offapi-0.1.2.dist-info/licenses/LICENSE
offapi/__init__.py
offapi/__version__.py
offapi/py.typed
offapi/redoc.js
offapi/scalar.js
offapi/swagger_bundle.js
offapi/swagger_preset.js
offapi/swagger_style.css
offapi/templates.py
offapi/url.json
offapi-0.1.2.dist-info/RECORD
