Metadata-Version: 2.4
Name: offapi
Version: 0.1.2
Summary: OpenAPI frontend render offline template.
Author-Email: Keming <kemingy94@gmail.com>
License-Expression: Apache-2.0
Classifier: Intended Audience :: Developers
Project-URL: Homepage, https://github.com/kemingy/offapi
Requires-Python: >=3.10
